{
  "type": "minecraft:crafting_shapeless",
  "category": "misc",
  "ingredients": [
    {
      "item": "minecraft:calcite"
    },
    {
      "item": "minecraft:calcite"
    },
    {
      "item": "minecraft:calcite"
    },
    {
      "item": "minecraft:calcite"
    },
    {
      "item": "minecraft:calcite"
    },
    {
      "item": "minecraft:yellow_dye"
    },
    {
      "item": "minecraft:white_dye"
    }
  ],
  "result": {
    "count": 6,
    "item": "bte:platform_calcite_indented"
  }
}